analysis/__init__.py
analysis/prepocessing.py
analysis/qualitative.py
analysis/quantitative.py
analysis/reporting.py
analysis/visualization.py
rid_ant-0.1.0.dist-info/LICENSE
rid_ant-0.1.0.dist-info/METADATA
rid_ant-0.1.0.dist-info/WHEEL
rid_ant-0.1.0.dist-info/top_level.txt
rid_ant-0.1.0.dist-info/RECORD
